function/__init__.py
function/function.py
test_package_pypi-0.1.0.dist-info/METADATA
test_package_pypi-0.1.0.dist-info/WHEEL
test_package_pypi-0.1.0.dist-info/top_level.txt
test_package_pypi-0.1.0.dist-info/RECORD
