Metadata-Version: 2.1
Name: test-package-pypi
Version: 0.1.0
Summary: A brief description of your package
Author: Saro
Author-email: lovito@qi4m.com
Classifier: Programming Language :: Python :: 3
Classifier: License :: OSI Approved :: MIT License
Classifier: Operating System :: OS Independent
